inmdbremsim/__init__.py
inmdbremsim/driver.py
inmdbremsim/messages.py
inmdbremsim/tests.py
inmdbremsim/utils.py
immdbremsim_pkg_Antun-0.0.1.dist-info/METADATA
immdbremsim_pkg_Antun-0.0.1.dist-info/WHEEL
immdbremsim_pkg_Antun-0.0.1.dist-info/top_level.txt
immdbremsim_pkg_Antun-0.0.1.dist-info/RECORD
