Metadata-Version: 2.1
Name: immdbremsim-pkg-Antun
Version: 0.0.1
Summary: Simple remote sim app
Home-page: https://github.com/pypa/sampleproject
Author: Antun Horvat
Author-email: antun.horvat@intis.hr
License: UNKNOWN
Platform: UNKNOWN
Classifier: Programming Language :: Python :: 3
Classifier: License :: OSI Approved :: MIT License
Classifier: Operating System :: OS Independent
Requires-Python: >=3.6
